ChemInformant/__init__.py
ChemInformant/api_helpers.py
ChemInformant/cheminfo_api.py
ChemInformant/cli.py
ChemInformant/constants.py
ChemInformant/models.py
ChemInformant/py.typed
ChemInformant/sql.py
cheminformant-2.4.3.dist-info/licenses/LICENSE
cheminformant-2.4.3.dist-info/METADATA
cheminformant-2.4.3.dist-info/WHEEL
cheminformant-2.4.3.dist-info/entry_points.txt
cheminformant-2.4.3.dist-info/top_level.txt
cheminformant-2.4.3.dist-info/RECORD
