Metadata-Version: 2.4
Name: ChemInformant
Version: 2.4.3
Summary: A robust and high-throughput Python client for the PubChem API, designed for automated data retrieval and analysis
Author-email: Zhiang He <ang@hezhiang.com>
License-Expression: MIT
Project-URL: Homepage, https://github.com/HzaCode/ChemInformant
Project-URL: Documentation, https://github.com/HzaCode/ChemInformant#readme
Project-URL: Issues, https://github.com/HzaCode/ChemInformant/issues
Keywords: chemistry,cheminformatics,pubchem,api,compound,drug,cache,pydantic,batch,smiles,sql
Classifier: Programming Language :: Python :: 3
Classifier: Programming Language :: Python :: 3.9
Classifier: Programming Language :: Python :: 3.10
Classifier: Programming Language :: Python :: 3.11
Classifier: Programming Language :: Python :: 3.12
Classifier: Programming Language :: Python :: 3.13
Classifier: Operating System :: OS Independent
Classifier: Topic :: Scientific/Engineering :: Chemistry
Requires-Python: >=3.9
License-File: LICENSE
Requires-Dist: requests>=2.25.0
Requires-Dist: requests-cache>=1.2.0
Requires-Dist: pydantic>=2.0
Requires-Dist: pandas>=1.5.0
Requires-Dist: sqlalchemy>=1.4
Requires-Dist: pystow>=0.7
Provides-Extra: plot
Requires-Dist: matplotlib>=3.1; extra == "plot"
Requires-Dist: Pillow>=10; extra == "plot"
Requires-Dist: seaborn>=0.12; extra == "plot"
Requires-Dist: scikit-learn>=1.1; extra == "plot"
Provides-Extra: all
Requires-Dist: ChemInformant[plot]; extra == "all"
Provides-Extra: dev
Requires-Dist: pytest>=7.0; extra == "dev"
Requires-Dist: pytest-mock>=3.5; extra == "dev"
Requires-Dist: pytest-cov>=2.12; extra == "dev"
Requires-Dist: pytest-benchmark>=4.0; extra == "dev"
Requires-Dist: ruff; extra == "dev"
Requires-Dist: mypy; extra == "dev"
Dynamic: license-file
